{"nm":"Boslaan","id":"Q18963283","nr":"2","beelden":[{"title":"In restaurant Strandpaviljoen wordt door mevrouw Reeder namens een stel oudere zwemmers Hein Berg\u00e9 gehuldigd voor zijn inspanningen tegen uitbreiding van de voorzieningen van het zwembad De IJzeren Man.  ","creator":"Janssens, Felix","date":"19\/8\/1988","isShownBy":"http:\/\/denbosch.hosting.deventit.net\/HttpHandler\/icoon.ico?file=21106932","isShownAt":"https:\/\/zoeken.erfgoedshertogenbosch.nl\/detail.php?id=14579473"},{"title":"De nieuwe gebouwen aan de IJzeren Man waaronder caf\u00e9\/restaurant\/partycentrum van Van der Leur.  ","creator":"Janssens, Felix","date":"6\/8\/1992","isShownBy":"http:\/\/denbosch.hosting.deventit.net\/HttpHandler\/icoon.ico?file=87101710","isShownAt":"https:\/\/zoeken.erfgoedshertogenbosch.nl\/detail.php?id=86470819"}]}