{"nm":"Zuidoosterfront","id":"Q18958168","nr":"2","beelden":[{"title":"Voorgevelwand tijdens verbouwingen  ","creator":"Zuiden, Fotopersbureau Het","date":"4\/10\/1974","isShownBy":"http:\/\/denbosch.hosting.deventit.net\/HttpHandler\/icoon.ico?file=21146604","isShownAt":"https:\/\/zoeken.erfgoedshertogenbosch.nl\/detail.php?id=14663367"},{"title":"Portret van mevrouw Dijk- van Hesse, met de drieling Veronica, Helena en Christina te 's-Hertogenbosch. ","creator":"Onbekend","date":"31\/12\/1925","isShownBy":"http:\/\/denbosch.hosting.deventit.net\/HttpHandler\/icoon.ico?icoonfromxmlbeschr=14848870","isShownAt":"https:\/\/zoeken.erfgoedshertogenbosch.nl\/detail.php?id=14848870"}]}