{"nm":"Elzenstraat","id":"Q19117170","nr":"3","beelden":[{"title":"Situatieschets betreffende grondverhuur Elzenstraat nr. 6 voor de wederopbouw van boerderijen.  ","creator":"Gemeentewerken","date":"9\/4\/1947","isShownBy":"http:\/\/denbosch.hosting.deventit.net\/HttpHandler\/icoon.ico?file=82563603","isShownAt":"https:\/\/zoeken.erfgoedshertogenbosch.nl\/detail.php?id=14612086"},{"title":"Grondruiling Elzenstraat\/Graafseweg nr. 15. Door A. van Vugt over te dragen aan de Gemeente sectie M nr. 17 (Elzenstraat). Door de Gemeente over te dragen aan A. van Vugt Sectie M gedeelten van de nrs. 49-50-51 en 26 (Graafseweg). In tweevoud.  ","creator":"Onbekend","date":"30\/9\/1951","isShownBy":"http:\/\/denbosch.hosting.deventit.net\/HttpHandler\/icoon.ico?file=91287530","isShownAt":"https:\/\/zoeken.erfgoedshertogenbosch.nl\/detail.php?id=15172873"},{"title":"De directeur van de Titus Brandsmaschool, J. Verbruggen (rechts), ziet hoe de politie het bordje, dat aangeeft dat het verboden is deze school buiten schoolruren te betreden, wordt bevestigd.  ","creator":"Janssens, Felix","date":"30\/6\/1988","isShownBy":"http:\/\/denbosch.hosting.deventit.net\/HttpHandler\/icoon.ico?file=21406003","isShownAt":"https:\/\/zoeken.erfgoedshertogenbosch.nl\/detail.php?id=15211339"}]}