{"nm":"Kasteeldreef","id":"Q19292454","nr":"5","beelden":[{"title":"Woonhuis. Opname in opdracht van Stienstra bv  ","creator":"Zuiden, Fotopersbureau Het","date":"13\/10\/1978","isShownBy":"http:\/\/denbosch.hosting.deventit.net\/HttpHandler\/icoon.ico?file=21226391","isShownAt":"https:\/\/zoeken.erfgoedshertogenbosch.nl\/detail.php?id=14832377"},{"title":"woonhuis  ","creator":"Zuiden, Fotopersbureau Het","date":"13\/10\/1978","isShownBy":"http:\/\/denbosch.hosting.deventit.net\/HttpHandler\/icoon.ico?file=21447778","isShownAt":"https:\/\/zoeken.erfgoedshertogenbosch.nl\/detail.php?id=15300592"},{"title":"Luchtopname van twee boerderijen aan de Kasteeldreef te Empel. ","creator":"Onbekend","date":"1\/1\/1947","isShownBy":"http:\/\/denbosch.hosting.deventit.net\/HttpHandler\/icoon.ico?file=748299598","isShownAt":"https:\/\/zoeken.erfgoedshertogenbosch.nl\/detail.php?id=284373554"},{"title":"Door en Willem Reuser bij hun woning aan de huidige Kasteeldreef te Empel, rechts dokter de Ridder uit Hedel. ","creator":"Onbekend","date":"1\/1\/1947","isShownBy":"http:\/\/denbosch.hosting.deventit.net\/HttpHandler\/icoon.ico?file=748299627","isShownAt":"https:\/\/zoeken.erfgoedshertogenbosch.nl\/detail.php?id=284396206"},{"title":"Luchtopname van boerderijen aan de Kasteeldreef te Empel. ","creator":"Onbekend","date":"","isShownBy":"http:\/\/denbosch.hosting.deventit.net\/HttpHandler\/icoon.ico?file=957472101","isShownAt":"https:\/\/zoeken.erfgoedshertogenbosch.nl\/detail.php?id=956747341"}]}