{"nm":"St Antoniestraatje","id":"Q19545022","nr":"2","beelden":[{"title":"Gezicht op de achterzijde van de kapel van Sint-Antonius.","creator":"Zuiden, Fotopersbureau Het","date":"17\/3\/1933","isShownBy":"http:\/\/denbosch.hosting.deventit.net\/HttpHandler\/icoon.ico?file=21041966","isShownAt":"https:\/\/zoeken.erfgoedshertogenbosch.nl\/detail.php?id=14443022"},{"title":"De winkels van A.C. Weckx en Van Deursen  ","creator":"Zuiden, Fotopersbureau Het","date":"31\/12\/1942","isShownBy":"http:\/\/denbosch.hosting.deventit.net\/HttpHandler\/icoon.ico?file=21127778","isShownAt":"https:\/\/zoeken.erfgoedshertogenbosch.nl\/detail.php?id=14624294"}]}