{"nm":"Tweede Korenstraatje","id":"Q19575009","nr":"52","beelden":[{"title":"Huis \"De Put\" op de hoek met de Dode Nieuwstraat, gezien vanuit de Karrenstraat. Links Caf\u00e9 Burgerlogement Peter.  ","creator":"Onbekend","date":"","isShownBy":"http:\/\/denbosch.hosting.deventit.net\/HttpHandler\/icoon.ico?file=21050378","isShownAt":"https:\/\/zoeken.erfgoedshertogenbosch.nl\/detail.php?id=14460553"},{"title":"Gevelwand aan de zuidzijde van de straat. De panden zijn in 1970 ten behoeve van nieuwbouw HEMA gesloopt.  ","creator":"Roelands, J.A.M.","date":"1969","isShownBy":"http:\/\/denbosch.hosting.deventit.net\/HttpHandler\/icoon.ico?file=21053217","isShownAt":"https:\/\/zoeken.erfgoedshertogenbosch.nl\/detail.php?id=14466386"},{"title":"Overzicht van de gesloopte zuidelijke helft van het straatje ten behoeve van nieuwbouw HEMA. ","creator":"Roelands, J.A.M.","date":"1970","isShownBy":"http:\/\/denbosch.hosting.deventit.net\/HttpHandler\/icoon.ico?file=21061948","isShownAt":"https:\/\/zoeken.erfgoedshertogenbosch.nl\/detail.php?id=14484686"},{"title":"Gevelwand van te slopen panden aan de zuidzijde van de straat, gezien in richting Dode Nieuwstraat. (Opname is gemaakt in opdracht van de Hema) ","creator":"Zuiden, Fotopersbureau Het","date":"12\/11\/1969","isShownBy":"http:\/\/denbosch.hosting.deventit.net\/HttpHandler\/icoon.ico?file=21089887","isShownAt":"https:\/\/zoeken.erfgoedshertogenbosch.nl\/detail.php?id=14543264"},{"title":"Bovengedeelte voorgevel huis 'In den Vijghboom' Ao 1632. In de muurankers:1706. ","creator":"Roelands, J.A.M.","date":"1969","isShownBy":"http:\/\/denbosch.hosting.deventit.net\/HttpHandler\/icoon.ico?file=21090351","isShownAt":"https:\/\/zoeken.erfgoedshertogenbosch.nl\/detail.php?id=14544262"},{"title":"0072257","creator":"Onbekend","date":"","isShownBy":"http:\/\/denbosch.hosting.deventit.net\/HttpHandler\/icoon.ico?file=21094903","isShownAt":"https:\/\/zoeken.erfgoedshertogenbosch.nl\/detail.php?id=14553965"},{"title":"Gevelsteen huis \"In de Put\"  ","creator":"Janssens, Felix","date":"21\/4\/1987","isShownBy":"http:\/\/denbosch.hosting.deventit.net\/HttpHandler\/icoon.ico?file=21101676","isShownAt":"https:\/\/zoeken.erfgoedshertogenbosch.nl\/detail.php?id=14568333"},{"title":"Bovenlicht van voordeur huis 'De Put'.  ","creator":"Roelands, J.A.M.","date":"1970","isShownBy":"http:\/\/denbosch.hosting.deventit.net\/HttpHandler\/icoon.ico?file=21104820","isShownAt":"https:\/\/zoeken.erfgoedshertogenbosch.nl\/detail.php?id=14575255"},{"title":"Gevelsteen van het huis In de Put, op de hoek met de Karrenstraat.  ","creator":"Zuiden, Fotopersbureau Het","date":"4\/2\/1941","isShownBy":"http:\/\/denbosch.hosting.deventit.net\/HttpHandler\/icoon.ico?file=21133864","isShownAt":"https:\/\/zoeken.erfgoedshertogenbosch.nl\/detail.php?id=14637118"},{"title":"Achterzijde van te slopen huizen aan de zuidzijde van de straat. (Opname in opdracht van Hema).  ","creator":"Zuiden, Fotopersbureau Het","date":"12\/11\/1969","isShownBy":"http:\/\/denbosch.hosting.deventit.net\/HttpHandler\/icoon.ico?file=21141086","isShownAt":"https:\/\/zoeken.erfgoedshertogenbosch.nl\/detail.php?id=14651934"},{"title":"Voor- en zijgevel huis \"De Put\" met op de voorgrond de Karrenstraat. Rechts de Dode Nieuwstraat.  ","creator":"Roelands, J.A.M.","date":"1965","isShownBy":"http:\/\/denbosch.hosting.deventit.net\/HttpHandler\/icoon.ico?file=21141581","isShownAt":"https:\/\/zoeken.erfgoedshertogenbosch.nl\/detail.php?id=14652888"},{"title":"Achtergevel huis \"In de Put\", gezien vanuit de Dode Nieuwstraat. (Opname in opdracht van Gemeentewerken).  ","creator":"Zuiden, Fotopersbureau Het","date":"4\/2\/1941","isShownBy":"http:\/\/denbosch.hosting.deventit.net\/HttpHandler\/icoon.ico?file=21156708","isShownAt":"https:\/\/zoeken.erfgoedshertogenbosch.nl\/detail.php?id=14684425"},{"title":"Rechts voorgevels huizen gezien in richting Hooge Steenweg. Rechts fietsenstallingen en -reparatieinrichtingen.  ","creator":"Sterk, M.","date":"31\/3\/1962","isShownBy":"http:\/\/denbosch.hosting.deventit.net\/HttpHandler\/icoon.ico?file=21160372","isShownAt":"https:\/\/zoeken.erfgoedshertogenbosch.nl\/detail.php?id=14692190"},{"title":"Daken en achterzijde van te slopen panden aan de zuidzijde van de straat. (Opname in opdracht van Hema).  ","creator":"Zuiden, Fotopersbureau Het","date":"12\/11\/1969","isShownBy":"http:\/\/denbosch.hosting.deventit.net\/HttpHandler\/icoon.ico?file=21168719","isShownAt":"https:\/\/zoeken.erfgoedshertogenbosch.nl\/detail.php?id=14709942"},{"title":"Tekening van een detail huis De Put.  ","creator":"Onbekend","date":"1670","isShownBy":"http:\/\/denbosch.hosting.deventit.net\/HttpHandler\/icoon.ico?file=21185289","isShownAt":"https:\/\/zoeken.erfgoedshertogenbosch.nl\/detail.php?id=14744886"},{"title":"0072256","creator":"Onbekend","date":"","isShownBy":"http:\/\/denbosch.hosting.deventit.net\/HttpHandler\/icoon.ico?file=21188275","isShownAt":"https:\/\/zoeken.erfgoedshertogenbosch.nl\/detail.php?id=14751029"},{"title":"Zijgevel HEMA aan de zuidzijde van het straatje.  ","creator":"Roelands, J.A.M.","date":"1973","isShownBy":"http:\/\/denbosch.hosting.deventit.net\/HttpHandler\/icoon.ico?file=21203615","isShownAt":"https:\/\/zoeken.erfgoedshertogenbosch.nl\/detail.php?id=14783668"},{"title":"Uithangbord 'De Kroon'.  ","creator":"Roelands, J.A.M.","date":"1960","isShownBy":"http:\/\/denbosch.hosting.deventit.net\/HttpHandler\/icoon.ico?file=21205861","isShownAt":"https:\/\/zoeken.erfgoedshertogenbosch.nl\/detail.php?id=14788683"},{"title":"Achtergevel van het huis In de Put op de hoek met de Karrenstraat, gezien vanuit de Dode Nieuwstraat.  ","creator":"Zuiden, Fotopersbureau Het","date":"4\/2\/1941","isShownBy":"http:\/\/denbosch.hosting.deventit.net\/HttpHandler\/icoon.ico?file=21206830","isShownAt":"https:\/\/zoeken.erfgoedshertogenbosch.nl\/detail.php?id=14790761"},{"title":"Overzicht van de gesloopte zuidelijke helft van het straatje ten behoeve van nieuwbouw HEMA.  ","creator":"Roelands, J.A.M.","date":"1970","isShownBy":"http:\/\/denbosch.hosting.deventit.net\/HttpHandler\/icoon.ico?file=21207346","isShownAt":"https:\/\/zoeken.erfgoedshertogenbosch.nl\/detail.php?id=14791804"},{"title":"Gezien vanaf de Dode Nieuwstraat in richting Markt.  ","creator":"Sterk, M.","date":"31\/8\/1961","isShownBy":"http:\/\/denbosch.hosting.deventit.net\/HttpHandler\/icoon.ico?file=21210909","isShownAt":"https:\/\/zoeken.erfgoedshertogenbosch.nl\/detail.php?id=14799236"},{"title":"Brand bij de fa. Driessen, touwhandel, mandenwerken, rietmeubelen, borstelwerken, sportvisserij-artikelen, huishoudartikelen. Op de hoek van het Tweede Korenstraatje. Links de voorgevel van het pand van de HEMA. ","creator":"Zuiden, Fotopersbureau Het","date":"22\/10\/1930","isShownBy":"http:\/\/denbosch.hosting.deventit.net\/HttpHandler\/icoon.ico?file=21241193","isShownAt":"https:\/\/zoeken.erfgoedshertogenbosch.nl\/detail.php?id=14864166"},{"title":"Gevelwand van te slopen panden aan de zuidzijde van de straat, gezien in richting Dode Nieuwstraat. (Opname in opdracht van Hema). ","creator":"Zuiden, Fotopersbureau Het","date":"12\/11\/1969","isShownBy":"http:\/\/denbosch.hosting.deventit.net\/HttpHandler\/icoon.ico?file=21248376","isShownAt":"https:\/\/zoeken.erfgoedshertogenbosch.nl\/detail.php?id=14879592"},{"title":"Plaatsing van 4 enkelzijdige reclameborden v\u00f3\u00f3r de zijgevel van de HEMA akkoord door B & W. ","creator":"Publex, Amsterdam","date":"1983","isShownBy":"http:\/\/denbosch.hosting.deventit.net\/HttpHandler\/icoon.ico?file=21254097","isShownAt":"https:\/\/zoeken.erfgoedshertogenbosch.nl\/detail.php?id=14891668"},{"title":"Gevelwand van te slopen panden aan de zuidzijde van de straat, gezien in richting Dode Nieuwstraat. (Opname in opdracht van Hema). ","creator":"Zuiden, Fotopersbureau Het","date":"12\/11\/1969","isShownBy":"http:\/\/denbosch.hosting.deventit.net\/HttpHandler\/icoon.ico?file=21255779","isShownAt":"https:\/\/zoeken.erfgoedshertogenbosch.nl\/detail.php?id=14895242"},{"title":"Achterzijde van te slopen panden aan de zuidzijde van de straat. (Opname in opdracht van Hema). ","creator":"Zuiden, Fotopersbureau Het","date":"12\/11\/1969","isShownBy":"http:\/\/denbosch.hosting.deventit.net\/HttpHandler\/icoon.ico?file=21257574","isShownAt":"https:\/\/zoeken.erfgoedshertogenbosch.nl\/detail.php?id=14898947"},{"title":"Diverse opnamen van de ruilbeurs van typisch Bossche dingen in het Kringhuis Vrienden van 's-Hertogenbosch. ","creator":"Janssens, Felix","date":"4\/10\/1987","isShownBy":"http:\/\/denbosch.hosting.deventit.net\/HttpHandler\/icoon.ico?file=21266649","isShownAt":"https:\/\/zoeken.erfgoedshertogenbosch.nl\/detail.php?id=14917683"},{"title":"Portret van fotograaf Jan Stalpers in het Kringhuis Vrienden van 's-Hertogenbosch. ","creator":"Janssens, Felix","date":"30\/7\/1987","isShownBy":"http:\/\/denbosch.hosting.deventit.net\/HttpHandler\/icoon.ico?file=21266991","isShownAt":"https:\/\/zoeken.erfgoedshertogenbosch.nl\/detail.php?id=14918405"},{"title":"Achterzijde van te slopen panden aan de zuidzijde van de straat. (Opname in opdracht van Hema).  ","creator":"Zuiden, Fotopersbureau Het","date":"12\/11\/1969","isShownBy":"http:\/\/denbosch.hosting.deventit.net\/HttpHandler\/icoon.ico?file=21285685","isShownAt":"https:\/\/zoeken.erfgoedshertogenbosch.nl\/detail.php?id=14958748"},{"title":"Gevelsteen van huis \"In de Put\" uit 1670. Voorstelling van Jezus en de Samaritaanse vrouw bij de put.  ","creator":"Onbekend","date":"","isShownBy":"http:\/\/denbosch.hosting.deventit.net\/HttpHandler\/icoon.ico?file=21296321","isShownAt":"https:\/\/zoeken.erfgoedshertogenbosch.nl\/detail.php?id=14981196"},{"title":"Schoorsteenvegers tijdens de kinderoptocht. Vijfde prijs in Groep B.  ","creator":"Zuiden, Fotopersbureau Het","date":"18\/2\/1958","isShownBy":"http:\/\/denbosch.hosting.deventit.net\/HttpHandler\/icoon.ico?file=21311706","isShownAt":"https:\/\/zoeken.erfgoedshertogenbosch.nl\/detail.php?id=15013577"},{"title":"Gevelwanden gezien in de richting van de Markt en Hooge Steenweg. Links cafetaria 't Centrum' en rechts enkele fietsenstallingen.  ","creator":"Sterk, M.","date":"31\/3\/1962","isShownBy":"http:\/\/denbosch.hosting.deventit.net\/HttpHandler\/icoon.ico?file=21315179","isShownAt":"https:\/\/zoeken.erfgoedshertogenbosch.nl\/detail.php?id=15020956"},{"title":"Hoekhuis \"De Put\" op de hoek met de Dode Nieuwstraat, gezien vanuit de Karrenstraat.","creator":"Onbekend","date":"","isShownBy":"http:\/\/denbosch.hosting.deventit.net\/HttpHandler\/icoon.ico?icoonfromxmlbeschr=15030468","isShownAt":"https:\/\/zoeken.erfgoedshertogenbosch.nl\/detail.php?id=15030468"},{"title":"Gevelwand aan de zuidzijde van de straat. De panden zijn in 1970  ten behoeve van nieuwbouw HEMA gesloopt.  ","creator":"Roelands, J.A.M.","date":"1969","isShownBy":"http:\/\/denbosch.hosting.deventit.net\/HttpHandler\/icoon.ico?file=21323823","isShownAt":"https:\/\/zoeken.erfgoedshertogenbosch.nl\/detail.php?id=15039531"},{"title":"Tekening van de voorgevel en topgevel met gevelsteen van het huis De Put. ","creator":"Huyver, J.J.C.","date":"31\/3\/1919","isShownBy":"http:\/\/denbosch.hosting.deventit.net\/HttpHandler\/icoon.ico?file=21335907","isShownAt":"https:\/\/zoeken.erfgoedshertogenbosch.nl\/detail.php?id=15065248"},{"title":"Gezien in zuidelijke richting vanuit de Karrenstraat. In het verlengde de Dode Nieuwstraat ","creator":"Zuiden, Fotopersbureau Het","date":"26\/1\/1935","isShownBy":"http:\/\/denbosch.hosting.deventit.net\/HttpHandler\/icoon.ico?file=21340546","isShownAt":"https:\/\/zoeken.erfgoedshertogenbosch.nl\/detail.php?id=15074776"},{"title":"Het huis In de Put, gezien vanuit de Karrenstraat. In het verlengde de Dode Nieuwstraat. ","creator":"Zuiden, Fotopersbureau Het","date":"23\/5\/1950","isShownBy":"http:\/\/denbosch.hosting.deventit.net\/HttpHandler\/icoon.ico?file=21342745","isShownAt":"https:\/\/zoeken.erfgoedshertogenbosch.nl\/detail.php?id=15079506"},{"title":"Achterzijde van te slopen panden aan de zuidzijde van de straat. (Opname in opdracht van Hema).  ","creator":"Zuiden, Fotopersbureau Het","date":"12\/11\/1969","isShownBy":"http:\/\/denbosch.hosting.deventit.net\/HttpHandler\/icoon.ico?file=21361066","isShownAt":"https:\/\/zoeken.erfgoedshertogenbosch.nl\/detail.php?id=15116412"},{"title":"Bovengedeelte achtergevel van het huis \"De Put\", gezien vanuit de Dode Nieuwstraat. Achtererf van het huis \"De Blaasbalg\" in de Kruisstraat.  ","creator":"Roelands, J.A.M.","date":"1985","isShownBy":"http:\/\/denbosch.hosting.deventit.net\/HttpHandler\/icoon.ico?file=21376516","isShownAt":"https:\/\/zoeken.erfgoedshertogenbosch.nl\/detail.php?id=15149172"},{"title":"Huis \"De Put\" op de hoek met de Dode Nieuwstraat.  In de geveltop het jaartal MDCLXXI. Op lagere gevelsteen Christus met de Samaritaanse vrouw bij de waterput.","creator":"Onbekend","date":"31\/12\/1930","isShownBy":"http:\/\/denbosch.hosting.deventit.net\/HttpHandler\/icoon.ico?icoonfromxmlbeschr=15155026","isShownAt":"https:\/\/zoeken.erfgoedshertogenbosch.nl\/detail.php?id=15155026"},{"title":"Voorgevels huizen, Dode Nieuwstraat, rechts.  ","creator":"Sterk, M.","date":"31\/3\/1962","isShownBy":"http:\/\/denbosch.hosting.deventit.net\/HttpHandler\/icoon.ico?file=21379906","isShownAt":"https:\/\/zoeken.erfgoedshertogenbosch.nl\/detail.php?id=15156298"},{"title":"Rechts een gedeelte zichtbaar van de Dode Nieuwstraat. In het midden huis \"De Put\".","creator":"Onbekend","date":"31\/12\/1950","isShownBy":"http:\/\/denbosch.hosting.deventit.net\/HttpHandler\/icoon.ico?icoonfromxmlbeschr=15176343","isShownAt":"https:\/\/zoeken.erfgoedshertogenbosch.nl\/detail.php?id=15176343"},{"title":"Huis \"In de Put\". Detail van lijstgevel in Empirestijl.  ","creator":"Zuiden, Fotopersbureau Het","date":"20\/9\/1943","isShownBy":"http:\/\/denbosch.hosting.deventit.net\/HttpHandler\/icoon.ico?file=21389733","isShownAt":"https:\/\/zoeken.erfgoedshertogenbosch.nl\/detail.php?id=15177100"},{"title":"Oude, onder het straatje doorlopende kelders, zichtbaar geworden na sloop van de zuidzijde van het straatje.  ","creator":"Roelands, J.A.M.","date":"1970","isShownBy":"http:\/\/denbosch.hosting.deventit.net\/HttpHandler\/icoon.ico?file=21404316","isShownAt":"https:\/\/zoeken.erfgoedshertogenbosch.nl\/detail.php?id=15207950"},{"title":"Rechts voorgevels van onder andere de fietsenstalling, gezien in richting Hooge Steenweg.  ","creator":"Sterk, M.","date":"31\/3\/1962","isShownBy":"http:\/\/denbosch.hosting.deventit.net\/HttpHandler\/icoon.ico?file=21409978","isShownAt":"https:\/\/zoeken.erfgoedshertogenbosch.nl\/detail.php?id=15219480"},{"title":"Gevelwand aan de zuidzijde van de straat met te slopen panden, gezien in richting Dode Nieuwstraat. (Opname in opdracht van Hema).  ","creator":"Zuiden, Fotopersbureau Het","date":"12\/11\/1969","isShownBy":"http:\/\/denbosch.hosting.deventit.net\/HttpHandler\/icoon.ico?file=21423806","isShownAt":"https:\/\/zoeken.erfgoedshertogenbosch.nl\/detail.php?id=15249371"},{"title":"Gevelwand van te slopen panden aan de zuidzijde van de straat, gezien in richting Markt\/Hooge Steenweg. (Opname in opdracht van Hema).  ","creator":"Zuiden, Fotopersbureau Het","date":"12\/11\/1969","isShownBy":"http:\/\/denbosch.hosting.deventit.net\/HttpHandler\/icoon.ico?file=21432954","isShownAt":"https:\/\/zoeken.erfgoedshertogenbosch.nl\/detail.php?id=15268999"},{"title":"Gezien in richting Dode Nieuwstraat.Links gevelwand van te slopen panden. (Opname in opdracht van Hema).  ","creator":"Zuiden, Fotopersbureau Het","date":"12\/11\/1969","isShownBy":"http:\/\/denbosch.hosting.deventit.net\/HttpHandler\/icoon.ico?file=21436364","isShownAt":"https:\/\/zoeken.erfgoedshertogenbosch.nl\/detail.php?id=15276323"},{"title":"Tentoonstelling \"Kerststallen van toen\" in het Kringhuis van de Kring Vrienden van 's-Hertogenbosch.  ","creator":"Janssens, Felix","date":"8\/12\/1990","isShownBy":"http:\/\/denbosch.hosting.deventit.net\/HttpHandler\/icoon.ico?file=21456603","isShownAt":"https:\/\/zoeken.erfgoedshertogenbosch.nl\/detail.php?id=15815190"},{"title":"Een kijkje bij de carnavalsexpositie in het Kringhuis van de Vrienden van 's-Hertogenbosch.","creator":"Janssens, Felix","date":"2\/2\/1994","isShownBy":"http:\/\/denbosch.hosting.deventit.net\/HttpHandler\/icoon.ico?file=955902506","isShownAt":"https:\/\/zoeken.erfgoedshertogenbosch.nl\/detail.php?id=753343352"},{"title":"Exterieur snoepwinkel de Bossche Suikeroom op Tweede Korenstraatje 18, gezien vanuit Karrenstraat. Rechts van snoepwinkel Dode Nieuwstraat. ","creator":"Beerens, Ad","date":"31\/7\/1998","isShownBy":"http:\/\/denbosch.hosting.deventit.net\/HttpHandler\/icoon.ico?file=1446709890","isShownAt":"https:\/\/zoeken.erfgoedshertogenbosch.nl\/detail.php?id=961893448"},{"title":"Prent van een huis op de hoek van het Tweede Korenstraatje en de Hooge Steenweg\/Pensmarkt, in de volksmond het hazewintje genoemd. Waarschijnlijk stamt het huis uit de veertiende eeuw. Op de afbeelding zit er een tabak- en snuifzaak in het huis. Het pand werd in 1835 afgebroken. ","creator":"Man, Anthonie Willem Hendrik Nolthenius de","date":"1842","isShownBy":"http:\/\/denbosch.hosting.deventit.net\/HttpHandler\/icoon.ico?icoonfromxmlbeschr=1451457456","isShownAt":"https:\/\/zoeken.erfgoedshertogenbosch.nl\/detail.php?id=1451457456"}]}